carmenPR/PR.py
carmenPR/__init__.py
carmenPR/expansiones/__init__.py
carmenpr-0.0.1.dist-info/licenses/LICENSE.md
carmenpr-0.0.1.dist-info/METADATA
carmenpr-0.0.1.dist-info/WHEEL
carmenpr-0.0.1.dist-info/top_level.txt
carmenpr-0.0.1.dist-info/RECORD
