Metadata-Version: 2.4
Name: carmenPR
Version: 0.0.1
Summary: Un paquete épico con funciones aleatorias para mis proyectos (y mucho odio hacia Carmen PR).
Home-page: https://github.com/carmenPR/odio
Author: XPro (Danito360)
Author-email: "XPro (Danito360)" <dani@duction.es>
License: # 💖 **LOVE LICENSE – “Ama y ensancha el alma”**
Keywords: hate,utilities,carmen,humor,epic,insultos,utils,duction
Requires-Python: >=3.7
License-File: LICENSE.md
Requires-Dist: colorama
Requires-Dist: rich
Requires-Dist: cowsay
Requires-Dist: requests
Dynamic: author
Dynamic: home-page
Dynamic: license-file
Dynamic: requires-python
